setup.py
openstreetmap_writer.egg-info/PKG-INFO
openstreetmap_writer.egg-info/SOURCES.txt
openstreetmap_writer.egg-info/dependency_links.txt
openstreetmap_writer.egg-info/requires.txt
openstreetmap_writer.egg-info/top_level.txt
osmwriter/__init__.py
osmwriter/_version.py
osmwriter/tests.py